MANIFEST.in
README.txt
package.json
project_config.json
setup.py
buildprof/__init__.py
buildprof/cmdline.py
buildprof/exporthtml.py
buildprof.egg-info/PKG-INFO
buildprof.egg-info/SOURCES.txt
buildprof.egg-info/dependency_links.txt
buildprof.egg-info/entry_points.txt
buildprof.egg-info/top_level.txt
buildprof/static/index.html
buildprof/static/font/FontAwesome.otf
buildprof/static/font/fontawesome-webfont.eot
buildprof/static/font/fontawesome-webfont.svg
buildprof/static/font/fontawesome-webfont.ttf
buildprof/static/font/fontawesome-webfont.woff
buildprof/static/img/favicon.ico
buildprof/static/scripts/scripts.min.js
buildprof/static/styles/styles.min.css