Metadata-Version: 1.0
Name: buildprof
Version: 0.1.7
Summary: Build profiling tools and UI
Home-page: https://pypi.python.org/pypi/buildprof
Author: Pierre Tardy
Author-email: pierre.tardy@intel.com
License: GNU GPL
Platform: UNKNOWN
